buf/__init__.py
buf/validate/validate_pb2_grpc.py
buf/validate/expression_pb2_grpc.py
buf/validate/expression_pb2.py
buf/validate/validate_pb2.py
buf/validate/expression_pb2.pyi
buf/validate/validate_pb2.pyi
buf/validate/__init__.py
buf/validate/priv/private_pb2.pyi
buf/validate/priv/private_pb2.py
buf/validate/priv/__init__.py
buf/validate/priv/private_pb2_grpc.py
dispatch_functions-0.0.14.dist-info/METADATA
dispatch_functions-0.0.14.dist-info/top_level.txt
dispatch_functions-0.0.14.dist-info/WHEEL
dispatch_functions-0.0.14.dist-info/RECORD
dispatch_functions-0.0.14.dist-info/LICENSE
dispatch/scheduler.py
dispatch/function.py
dispatch/id.py
dispatch/status.py
dispatch/proto.py
dispatch/error.py
dispatch/fastapi.py
dispatch/coroutine.py
dispatch/__init__.py
dispatch/client.py
dispatch/experimental/__init__.py
dispatch/experimental/durable/function.py
dispatch/experimental/durable/frame.pyi
dispatch/experimental/durable/frame.cpython-312-s390x-linux-gnu.so
dispatch/experimental/durable/__init__.py
dispatch/experimental/durable/frame.c
dispatch/experimental/durable/registry.py
dispatch/integrations/httpx.py
dispatch/integrations/http.py
dispatch/integrations/requests.py
dispatch/integrations/__init__.py
dispatch/signature/request.py
dispatch/signature/digest.py
dispatch/signature/key.py
dispatch/signature/__init__.py
dispatch/test/server.py
dispatch/test/__init__.py
dispatch/test/client.py
dispatch/test/service.py
dispatch/sdk/__init__.py
dispatch/sdk/v1/dispatch_pb2.py
dispatch/sdk/v1/call_pb2.pyi
dispatch/sdk/v1/poll_pb2.py
dispatch/sdk/v1/exit_pb2.py
dispatch/sdk/v1/exit_pb2_grpc.py
dispatch/sdk/v1/exit_pb2.pyi
dispatch/sdk/v1/error_pb2.py
dispatch/sdk/v1/call_pb2_grpc.py
dispatch/sdk/v1/poll_pb2.pyi
dispatch/sdk/v1/call_pb2.py
dispatch/sdk/v1/status_pb2.py
dispatch/sdk/v1/function_pb2.pyi
dispatch/sdk/v1/error_pb2_grpc.py
dispatch/sdk/v1/dispatch_pb2_grpc.py
dispatch/sdk/v1/function_pb2_grpc.py
dispatch/sdk/v1/__init__.py
dispatch/sdk/v1/poll_pb2_grpc.py
dispatch/sdk/v1/function_pb2.py
dispatch/sdk/v1/status_pb2.pyi
dispatch/sdk/v1/dispatch_pb2.pyi
dispatch/sdk/v1/status_pb2_grpc.py
dispatch/sdk/v1/error_pb2.pyi
